{"id_art": "4209fd0f7c40e5f31313065c0d41f27f", "title": "Notre-Dame-des-Landes : plus de 400 gendarmes deployes autour de la ZAD", "newspaper": "NouvelObservateur", "author": ["L'Obs"], "date_publi": "2018-01-17", "content": {"1": {"word": "Journee", "lemma": "journee", "pos_tag": "PROPN", "type_entity": "", "position": 1, "title": false}, "2": {"word": "cruciale", "lemma": "cruciale", "pos_tag": "ADJ", "type_entity": "", "position": 2, "title": false}, "3": {"word": "a", "lemma": "a", "pos_tag": "STOPWORD", "type_entity": "", "position": 3, "title": false}, "4": {"word": "NotreDamedesLandes", "lemma": "notredamedeslandes", "pos_tag": "PROPN", "type_entity": "", "position": 4, "title": false}, "5": {"word": ".", "lemma": ".", "pos_tag": "PUNCT", "type_entity": "", "position": 5, "title": false}, "6": {"word": "Le", "lemma": "le", "pos_tag": "STOPWORD", "type_entity": "", "position": 6, "title": false}, "7": {"word": "dispositif", "lemma": "dispositif", "pos_tag": "NOUN", "type_entity": "", "position": 7, "title": false}, "8": {"word": "policier", "lemma": "policier", "pos_tag": "ADJ", "type_entity": "", "position": 8, "title": false}, "9": {"word": "se", "lemma": "se", "pos_tag": "STOPWORD", "type_entity": "", "position": 9, "title": false}, "10": {"word": "met", "lemma": "met", "pos_tag": "SYM", "type_entity": "", "position": 10, "title": false}, "11": {"word": "progressivement", "lemma": "progressivement", "pos_tag": "ADV", "type_entity": "", "position": 11, "title": false}, "12": {"word": "en", "lemma": "en", "pos_tag": "STOPWORD", "type_entity": "", "position": 12, "title": false}, "13": {"word": "place", "lemma": "place", "pos_tag": "NOUN", "type_entity": "", "position": 13, "title": false}, "14": {"word": "autour", "lemma": "autour", "pos_tag": "ADV", "type_entity": "", "position": 14, "title": true}, "15": {"word": "de", "lemma": "de", "pos_tag": "STOPWORD", "type_entity": "", "position": 15, "title": true}, "16": {"word": "la", "lemma": "la", "pos_tag": "STOPWORD", "type_entity": "", "position": 16, "title": true}, "17": {"word": "ZAD", "lemma": "zad", "pos_tag": "NOUN", "type_entity": "", "position": 17, "title": true}, "18": {"word": "ce", "lemma": "ce", "pos_tag": "STOPWORD", "type_entity": "", "position": 18, "title": false}, "19": {"word": "mercredi", "lemma": "mercredi", "pos_tag": "NOUN", "type_entity": "", "position": 19, "title": false}, "20": {"word": "mercredi17janvieralors", "lemma": "mercredi17janvieralors", "pos_tag": "ADV", "type_entity": "", "position": 20, "title": false}, "21": {"word": "que", "lemma": "que", "pos_tag": "STOPWORD", "type_entity": "", "position": 21, "title": false}, "22": {"word": "la", "lemma": "la", "pos_tag": "STOPWORD", "type_entity": "", "position": 22, "title": true}, "23": {"word": "decision", "lemma": "decision", "pos_tag": "NOUN", "type_entity": "", "position": 23, "title": false}, "24": {"word": "du", "lemma": "du", "pos_tag": "STOPWORD", "type_entity": "", "position": 24, "title": false}, "25": {"word": "gouvernement", "lemma": "gouvernement", "pos_tag": "NOUN", "type_entity": "", "position": 25, "title": false}, "26": {"word": "pourrait", "lemma": "pourrait", "pos_tag": "STOPWORD", "type_entity": "", "position": 26, "title": false}, "27": {"word": "etre", "lemma": "etre", "pos_tag": "ADJ", "type_entity": "", "position": 27, "title": false}, "28": {"word": "annoncee", "lemma": "annoncee", "pos_tag": "SYM", "type_entity": "", "position": 28, "title": false}, "29": {"word": "en", "lemma": "en", "pos_tag": "STOPWORD", "type_entity": "", "position": 29, "title": false}, "30": {"word": "fin", "lemma": "fin", "pos_tag": "NOUN", "type_entity": "", "position": 30, "title": false}, "31": {"word": "de", "lemma": "de", "pos_tag": "STOPWORD", "type_entity": "", "position": 31, "title": true}, "32": {"word": "matinee", "lemma": "matinee", "pos_tag": "NOUN", "type_entity": "", "position": 32, "title": false}, "33": {"word": ".", "lemma": ".", "pos_tag": "PUNCT", "type_entity": "", "position": 33, "title": false}, "34": {"word": "Survolee", "lemma": "survolee", "pos_tag": "PROPN", "type_entity": "", "position": 34, "title": false}, "35": {"word": "par", "lemma": "par", "pos_tag": "STOPWORD", "type_entity": "", "position": 35, "title": false}, "36": {"word": "des", "lemma": "des", "pos_tag": "STOPWORD", "type_entity": "", "position": 36, "title": false}, "37": {"word": "helicopteres", "lemma": "helicopteres", "pos_tag": "NOUN", "type_entity": "", "position": 37, "title": false}, "38": {"word": "de", "lemma": "de", "pos_tag": "STOPWORD", "type_entity": "", "position": 38, "title": true}, "39": {"word": "la", "lemma": "la", "pos_tag": "STOPWORD", "type_entity": "", "position": 39, "title": true}, "40": {"word": "gendarmerie", "lemma": "gendarmerie", "pos_tag": "NOUN", "type_entity": "", "position": 40, "title": false}, "41": {"word": "la", "lemma": "la", "pos_tag": "STOPWORD", "type_entity": "", "position": 41, "title": true}, "42": {"word": "zone", "lemma": "zone", "pos_tag": "NOUN", "type_entity": "", "position": 42, "title": false}, "43": {"word": "d", "lemma": "d", "pos_tag": "STOPWORD", "type_entity": "", "position": 43, "title": false}, "44": {"word": "amenagement", "lemma": "amenagement", "pos_tag": "ADV", "type_entity": "", "position": 44, "title": false}, "45": {"word": "differe", "lemma": "differe", "pos_tag": "ADJ", "type_entity": "", "position": 45, "title": false}, "46": {"word": "est", "lemma": "est", "pos_tag": "STOPWORD", "type_entity": "", "position": 46, "title": false}, "47": {"word": "egalement", "lemma": "egalement", "pos_tag": "ADV", "type_entity": "", "position": 47, "title": false}, "48": {"word": "encerclee", "lemma": "encerclee", "pos_tag": "SYM", "type_entity": "", "position": 48, "title": false}, "49": {"word": "par", "lemma": "par", "pos_tag": "STOPWORD", "type_entity": "", "position": 49, "title": false}, "50": {"word": "sept", "lemma": "sept", "pos_tag": "STOPWORD", "type_entity": "", "position": 50, "title": false}, "51": {"word": "escadrons", "lemma": "escadrons", "pos_tag": "NOUN", "type_entity": "", "position": 51, "title": false}, "52": {"word": "soit", "lemma": "soit", "pos_tag": "STOPWORD", "type_entity": "", "position": 52, "title": false}, "53": {"word": "455", "lemma": "455", "pos_tag": "NUM", "type_entity": "", "position": 53, "title": false}, "54": {"word": "gendarmes", "lemma": "gendarmes", "pos_tag": "NOUN", "type_entity": "", "position": 54, "title": true}, "55": {"word": "mobiles", "lemma": "mobiles", "pos_tag": "ADJ", "type_entity": "", "position": 55, "title": false}, "56": {"word": "precise", "lemma": "precise", "pos_tag": "ADJ", "type_entity": "", "position": 56, "title": false}, "57": {"word": "BFMTV", "lemma": "bfmtv", "pos_tag": "PROPN", "type_entity": "", "position": 57, "title": false}, "58": {"word": ".", "lemma": ".", "pos_tag": "PUNCT", "type_entity": "", "position": 58, "title": false}, "59": {"word": "Un", "lemma": "un", "pos_tag": "DET", "type_entity": "", "position": 59, "title": false}, "60": {"word": "deploiement", "lemma": "deploiement", "pos_tag": "NOUN", "type_entity": "", "position": 60, "title": false}, "61": {"word": "qui", "lemma": "qui", "pos_tag": "STOPWORD", "type_entity": "", "position": 61, "title": false}, "62": {"word": "vise", "lemma": "vise", "pos_tag": "SYM", "type_entity": "", "position": 62, "title": false}, "63": {"word": "a", "lemma": "a", "pos_tag": "STOPWORD", "type_entity": "", "position": 63, "title": false}, "64": {"word": "controler", "lemma": "controler", "pos_tag": "SYM", "type_entity": "", "position": 64, "title": false}, "65": {"word": "et", "lemma": "et", "pos_tag": "STOPWORD", "type_entity": "", "position": 65, "title": false}, "66": {"word": "securiser", "lemma": "securiser", "pos_tag": "SYM", "type_entity": "", "position": 66, "title": false}, "67": {"word": "la", "lemma": "la", "pos_tag": "STOPWORD", "type_entity": "", "position": 67, "title": true}, "68": {"word": "zone", "lemma": "zone", "pos_tag": "NOUN", "type_entity": "", "position": 68, "title": false}, "69": {"word": "de", "lemma": "de", "pos_tag": "STOPWORD", "type_entity": "", "position": 69, "title": true}, "70": {"word": "1_600", "lemma": "1_600", "pos_tag": "NUM", "type_entity": "", "position": 70, "title": false}, "71": {"word": "hectares", "lemma": "hectares", "pos_tag": "NOUN", "type_entity": "", "position": 71, "title": false}, "72": {"word": "en", "lemma": "en", "pos_tag": "STOPWORD", "type_entity": "", "position": 72, "title": false}, "73": {"word": "prevision", "lemma": "prevision", "pos_tag": "NOUN", "type_entity": "", "position": 73, "title": false}, "74": {"word": "d", "lemma": "d", "pos_tag": "STOPWORD", "type_entity": "", "position": 74, "title": false}, "75": {"word": "une", "lemma": "une", "pos_tag": "STOPWORD", "type_entity": "", "position": 75, "title": false}, "76": {"word": "eventuelle", "lemma": "eventuelle", "pos_tag": "ADJ", "type_entity": "", "position": 76, "title": false}, "77": {"word": "evacuation", "lemma": "evacuation", "pos_tag": "NOUN", "type_entity": "", "position": 77, "title": false}, "78": {"word": ".", "lemma": ".", "pos_tag": "PUNCT", "type_entity": "", "position": 78, "title": false}, "79": {"word": "Selon", "lemma": "selon", "pos_tag": "STOPWORD", "type_entity": "", "position": 79, "title": false}, "80": {"word": "l", "lemma": "l", "pos_tag": "STOPWORD", "type_entity": "", "position": 80, "title": false}, "81": {"word": "AFP", "lemma": "afp", "pos_tag": "PROPN", "type_entity": "", "position": 81, "title": false}, "82": {"word": "plusieurs", "lemma": "plusieurs", "pos_tag": "STOPWORD", "type_entity": "", "position": 82, "title": false}, "83": {"word": "compagnies", "lemma": "compagnies", "pos_tag": "NOUN", "type_entity": "", "position": 83, "title": false}, "84": {"word": "de", "lemma": "de", "pos_tag": "STOPWORD", "type_entity": "", "position": 84, "title": true}, "85": {"word": "CRS", "lemma": "crs", "pos_tag": "PROPN", "type_entity": "", "position": 85, "title": false}, "86": {"word": "sont", "lemma": "sont", "pos_tag": "STOPWORD", "type_entity": "", "position": 86, "title": false}, "87": {"word": "egalement", "lemma": "egalement", "pos_tag": "SYM", "type_entity": "", "position": 87, "title": false}, "88": {"word": "en", "lemma": "en", "pos_tag": "STOPWORD", "type_entity": "", "position": 88, "title": false}, "89": {"word": "cours", "lemma": "cours", "pos_tag": "NOUN", "type_entity": "", "position": 89, "title": false}, "90": {"word": "de", "lemma": "de", "pos_tag": "STOPWORD", "type_entity": "", "position": 90, "title": true}, "91": {"word": "positionnement", "lemma": "positionnement", "pos_tag": "NOUN", "type_entity": "", "position": 91, "title": false}, "92": {"word": "a", "lemma": "a", "pos_tag": "STOPWORD", "type_entity": "", "position": 92, "title": false}, "93": {"word": "Nantes", "lemma": "nantes", "pos_tag": "PROPN", "type_entity": "", "position": 93, "title": false}, "94": {"word": "et", "lemma": "et", "pos_tag": "STOPWORD", "type_entity": "", "position": 94, "title": false}, "95": {"word": "Rennes", "lemma": "rennes", "pos_tag": "PROPN", "type_entity": "", "position": 95, "title": false}, "96": {"word": "au", "lemma": "au", "pos_tag": "STOPWORD", "type_entity": "", "position": 96, "title": false}, "97": {"word": "cas", "lemma": "cas", "pos_tag": "NOUN", "type_entity": "", "position": 97, "title": false}, "98": {"word": "ou", "lemma": "ou", "pos_tag": "STOPWORD", "type_entity": "", "position": 98, "title": false}, "99": {"word": "des", "lemma": "des", "pos_tag": "STOPWORD", "type_entity": "", "position": 99, "title": false}, "100": {"word": "manifestations", "lemma": "manifestations", "pos_tag": "NOUN", "type_entity": "", "position": 100, "title": false}, "101": {"word": "seraient", "lemma": "seraient", "pos_tag": "STOPWORD", "type_entity": "", "position": 101, "title": false}, "102": {"word": "organisees", "lemma": "organisees", "pos_tag": "ADJ", "type_entity": "", "position": 102, "title": false}, "103": {"word": "a", "lemma": "a", "pos_tag": "STOPWORD", "type_entity": "", "position": 103, "title": false}, "104": {"word": "la", "lemma": "la", "pos_tag": "STOPWORD", "type_entity": "", "position": 104, "title": true}, "105": {"word": "suite", "lemma": "suite", "pos_tag": "NOUN", "type_entity": "", "position": 105, "title": false}, "106": {"word": "de", "lemma": "de", "pos_tag": "STOPWORD", "type_entity": "", "position": 106, "title": true}, "107": {"word": "la", "lemma": "la", "pos_tag": "STOPWORD", "type_entity": "", "position": 107, "title": true}, "108": {"word": "decision", "lemma": "decision", "pos_tag": "NOUN", "type_entity": "", "position": 108, "title": false}, "109": {"word": "du", "lemma": "du", "pos_tag": "STOPWORD", "type_entity": "", "position": 109, "title": false}, "110": {"word": "l", "lemma": "l", "pos_tag": "STOPWORD", "type_entity": "", "position": 110, "title": false}, "111": {"word": "executif", "lemma": "executif", "pos_tag": "NOUN", "type_entity": "", "position": 111, "title": false}, "112": {"word": ".", "lemma": ".", "pos_tag": "PUNCT", "type_entity": "", "position": 112, "title": false}, "113": {"word": "Car", "lemma": "car", "pos_tag": "CCONJ", "type_entity": "", "position": 113, "title": false}, "114": {"word": "quelque", "lemma": "quelque", "pos_tag": "STOPWORD", "type_entity": "", "position": 114, "title": false}, "115": {"word": "soit", "lemma": "soit", "pos_tag": "STOPWORD", "type_entity": "", "position": 115, "title": false}, "116": {"word": "la", "lemma": "la", "pos_tag": "STOPWORD", "type_entity": "", "position": 116, "title": true}, "117": {"word": "reponse", "lemma": "reponse", "pos_tag": "NOUN", "type_entity": "", "position": 117, "title": false}, "118": {"word": "du", "lemma": "du", "pos_tag": "STOPWORD", "type_entity": "", "position": 118, "title": false}, "119": {"word": "gouvernement", "lemma": "gouvernement", "pos_tag": "NOUN", "type_entity": "", "position": 119, "title": false}, "120": {"word": "celleci", "lemma": "celleci", "pos_tag": "ADJ", "type_entity": "", "position": 120, "title": false}, "121": {"word": "sera", "lemma": "sera", "pos_tag": "STOPWORD", "type_entity": "", "position": 121, "title": false}, "122": {"word": "mauvaise", "lemma": "mauvaise", "pos_tag": "ADJ", "type_entity": "", "position": 122, "title": false}, "123": {"word": "pour", "lemma": "pour", "pos_tag": "STOPWORD", "type_entity": "", "position": 123, "title": false}, "124": {"word": "certains", "lemma": "certains", "pos_tag": "PRON", "type_entity": "", "position": 124, "title": false}, "125": {"word": "avait", "lemma": "avait", "pos_tag": "STOPWORD", "type_entity": "", "position": 125, "title": false}, "126": {"word": "reconnu", "lemma": "reconnu", "pos_tag": "SYM", "type_entity": "", "position": 126, "title": false}, "127": {"word": "des", "lemma": "des", "pos_tag": "STOPWORD", "type_entity": "", "position": 127, "title": false}, "128": {"word": "mardi", "lemma": "mardi", "pos_tag": "NOUN", "type_entity": "", "position": 128, "title": false}, "129": {"word": "le", "lemma": "le", "pos_tag": "STOPWORD", "type_entity": "", "position": 129, "title": false}, "130": {"word": "Premier", "lemma": "premier", "pos_tag": "ADJ", "type_entity": "", "position": 130, "title": false}, "131": {"word": "ministre", "lemma": "ministre", "pos_tag": "NOUN", "type_entity": "", "position": 131, "title": false}, "132": {"word": "Edouard", "lemma": "edouard", "pos_tag": "PROPN", "type_entity": "", "position": 132, "title": false}, "133": {"word": "Philippe", "lemma": "philippe", "pos_tag": "PROPN", "type_entity": "", "position": 133, "title": false}, "134": {"word": "devant", "lemma": "devant", "pos_tag": "STOPWORD", "type_entity": "", "position": 134, "title": false}, "135": {"word": "les", "lemma": "les", "pos_tag": "STOPWORD", "type_entity": "", "position": 135, "title": false}, "136": {"word": "deputes", "lemma": "deputes", "pos_tag": "NOUN", "type_entity": "", "position": 136, "title": false}, "137": {"word": "LREM", "lemma": "lrem", "pos_tag": "PROPN", "type_entity": "", "position": 137, "title": false}, "138": {"word": "en", "lemma": "en", "pos_tag": "STOPWORD", "type_entity": "", "position": 138, "title": false}, "139": {"word": "reunion", "lemma": "reunion", "pos_tag": "NOUN", "type_entity": "", "position": 139, "title": false}, "140": {"word": "de", "lemma": "de", "pos_tag": "STOPWORD", "type_entity": "", "position": 140, "title": true}, "141": {"word": "groupe", "lemma": "groupe", "pos_tag": "NOUN", "type_entity": "", "position": 141, "title": false}, "142": {"word": ".", "lemma": ".", "pos_tag": "PUNCT", "type_entity": "", "position": 142, "title": false}, "143": {"word": "La", "lemma": "la", "pos_tag": "STOPWORD", "type_entity": "", "position": 143, "title": true}, "144": {"word": "ZAD", "lemma": "zad", "pos_tag": "PROPN", "type_entity": "", "position": 144, "title": true}, "145": {"word": "est", "lemma": "est", "pos_tag": "STOPWORD", "type_entity": "", "position": 145, "title": false}, "146": {"word": "actuellement", "lemma": "actuellement", "pos_tag": "ADV", "type_entity": "", "position": 146, "title": false}, "147": {"word": "occupee", "lemma": "occupee", "pos_tag": "SYM", "type_entity": "", "position": 147, "title": false}, "148": {"word": "par", "lemma": "par", "pos_tag": "STOPWORD", "type_entity": "", "position": 148, "title": false}, "149": {"word": "150", "lemma": "150", "pos_tag": "NUM", "type_entity": "", "position": 149, "title": false}, "150": {"word": "a", "lemma": "a", "pos_tag": "STOPWORD", "type_entity": "", "position": 150, "title": false}, "151": {"word": "2_0", "lemma": "2_0", "pos_tag": "NUM", "type_entity": "", "position": 151, "title": false}, "152": {"word": "personnes", "lemma": "personnes", "pos_tag": "NOUN", "type_entity": "", "position": 152, "title": false}, "153": {"word": "qui", "lemma": "qui", "pos_tag": "STOPWORD", "type_entity": "", "position": 153, "title": false}, "154": {"word": "selon", "lemma": "selon", "pos_tag": "STOPWORD", "type_entity": "", "position": 154, "title": false}, "155": {"word": "les", "lemma": "les", "pos_tag": "STOPWORD", "type_entity": "", "position": 155, "title": false}, "156": {"word": "autorites", "lemma": "autorites", "pos_tag": "NOUN", "type_entity": "", "position": 156, "title": false}, "157": {"word": "en", "lemma": "en", "pos_tag": "STOPWORD", "type_entity": "", "position": 157, "title": false}, "158": {"word": "ont", "lemma": "ont", "pos_tag": "STOPWORD", "type_entity": "", "position": 158, "title": false}, "159": {"word": "fait", "lemma": "fait", "pos_tag": "STOPWORD", "type_entity": "", "position": 159, "title": false}, "160": {"word": "un", "lemma": "un", "pos_tag": "STOPWORD", "type_entity": "", "position": 160, "title": false}, "161": {"word": "camp", "lemma": "camp", "pos_tag": "NOUN", "type_entity": "", "position": 161, "title": false}, "162": {"word": "retranche", "lemma": "retranche", "pos_tag": "ADJ", "type_entity": "", "position": 162, "title": false}, "163": {"word": ".", "lemma": ".", "pos_tag": "PUNCT", "type_entity": "", "position": 163, "title": false}, "164": {"word": "La", "lemma": "la", "pos_tag": "STOPWORD", "type_entity": "", "position": 164, "title": true}, "165": {"word": "zone", "lemma": "zone", "pos_tag": "NOUN", "type_entity": "", "position": 165, "title": false}, "166": {"word": "sera", "lemma": "sera", "pos_tag": "STOPWORD", "type_entity": "", "position": 166, "title": false}, "167": {"word": "evacuee", "lemma": "evacuee", "pos_tag": "SYM", "type_entity": "", "position": 167, "title": false}, "168": {"word": "des", "lemma": "des", "pos_tag": "STOPWORD", "type_entity": "", "position": 168, "title": false}, "169": {"word": "elements", "lemma": "elements", "pos_tag": "NOUN", "type_entity": "", "position": 169, "title": false}, "170": {"word": "les", "lemma": "les", "pos_tag": "STOPWORD", "type_entity": "", "position": 170, "title": false}, "171": {"word": "plus", "lemma": "plus", "pos_tag": "STOPWORD", "type_entity": "", "position": 171, "title": true}, "172": {"word": "radicaux", "lemma": "radicaux", "pos_tag": "ADJ", "type_entity": "", "position": 172, "title": false}, "173": {"word": "a", "lemma": "a", "pos_tag": "STOPWORD", "type_entity": "", "position": 173, "title": false}, "174": {"word": "affirme", "lemma": "affirme", "pos_tag": "SYM", "type_entity": "", "position": 174, "title": false}, "175": {"word": "mardi", "lemma": "mardi", "pos_tag": "NOUN", "type_entity": "", "position": 175, "title": false}, "176": {"word": "le", "lemma": "le", "pos_tag": "STOPWORD", "type_entity": "", "position": 176, "title": false}, "177": {"word": "ministre", "lemma": "ministre", "pos_tag": "NOUN", "type_entity": "", "position": 177, "title": false}, "178": {"word": "de", "lemma": "de", "pos_tag": "STOPWORD", "type_entity": "", "position": 178, "title": true}, "179": {"word": "l", "lemma": "l", "pos_tag": "STOPWORD", "type_entity": "", "position": 179, "title": false}, "180": {"word": "Interieur", "lemma": "interieur", "pos_tag": "NOUN", "type_entity": "", "position": 180, "title": false}, "181": {"word": "Gerard", "lemma": "gerard", "pos_tag": "PROPN", "type_entity": "", "position": 181, "title": false}, "182": {"word": "Collomb", "lemma": "collomb", "pos_tag": "PROPN", "type_entity": "", "position": 182, "title": false}, "183": {"word": "sur", "lemma": "sur", "pos_tag": "STOPWORD", "type_entity": "", "position": 183, "title": false}, "184": {"word": "France", "lemma": "france", "pos_tag": "PROPN", "type_entity": "", "position": 184, "title": false}, "185": {"word": "2", "lemma": "2", "pos_tag": "NUM", "type_entity": "", "position": 185, "title": false}, "186": {"word": ".", "lemma": ".", "pos_tag": "PUNCT", "type_entity": "", "position": 186, "title": false}, "187": {"word": "Qu", "lemma": "qu", "pos_tag": "SCONJ", "type_entity": "", "position": 187, "title": false}, "188": {"word": "ils", "lemma": "ils", "pos_tag": "STOPWORD", "type_entity": "", "position": 188, "title": false}, "189": {"word": "soient", "lemma": "soient", "pos_tag": "STOPWORD", "type_entity": "", "position": 189, "title": false}, "190": {"word": "pour", "lemma": "pour", "pos_tag": "STOPWORD", "type_entity": "", "position": 190, "title": false}, "191": {"word": "ou", "lemma": "ou", "pos_tag": "STOPWORD", "type_entity": "", "position": 191, "title": false}, "192": {"word": "contre", "lemma": "contre", "pos_tag": "STOPWORD", "type_entity": "", "position": 192, "title": false}, "193": {"word": "l", "lemma": "l", "pos_tag": "STOPWORD", "type_entity": "", "position": 193, "title": false}, "194": {"word": "aeroport", "lemma": "aeroport", "pos_tag": "NOUN", "type_entity": "", "position": 194, "title": false}, "195": {"word": "la", "lemma": "la", "pos_tag": "STOPWORD", "type_entity": "", "position": 195, "title": true}, "196": {"word": "quasitotalite", "lemma": "quasitotalite", "pos_tag": "NOUN", "type_entity": "", "position": 196, "title": false}, "197": {"word": "des", "lemma": "des", "pos_tag": "STOPWORD", "type_entity": "", "position": 197, "title": false}, "198": {"word": "elus", "lemma": "elus", "pos_tag": "NOUN", "type_entity": "", "position": 198, "title": false}, "199": {"word": "locaux", "lemma": "locaux", "pos_tag": "ADJ", "type_entity": "", "position": 199, "title": false}, "200": {"word": "defendent", "lemma": "defendent", "pos_tag": "SYM", "type_entity": "", "position": 200, "title": false}, "201": {"word": "son", "lemma": "son", "pos_tag": "STOPWORD", "type_entity": "", "position": 201, "title": false}, "202": {"word": "evacuation", "lemma": "evacuation", "pos_tag": "NOUN", "type_entity": "", "position": 202, "title": false}, "203": {"word": "six", "lemma": "six", "pos_tag": "STOPWORD", "type_entity": "", "position": 203, "title": false}, "204": {"word": "ans", "lemma": "ans", "pos_tag": "NOUN", "type_entity": "", "position": 204, "title": false}, "205": {"word": "apres", "lemma": "apres", "pos_tag": "ADP", "type_entity": "", "position": 205, "title": false}, "206": {"word": "le", "lemma": "le", "pos_tag": "STOPWORD", "type_entity": "", "position": 206, "title": false}, "207": {"word": "fiasco", "lemma": "fiasco", "pos_tag": "NOUN", "type_entity": "", "position": 207, "title": false}, "208": {"word": "d", "lemma": "d", "pos_tag": "STOPWORD", "type_entity": "", "position": 208, "title": false}, "209": {"word": "une", "lemma": "une", "pos_tag": "STOPWORD", "type_entity": "", "position": 209, "title": false}, "210": {"word": "premiere", "lemma": "premiere", "pos_tag": "NOUN", "type_entity": "", "position": 210, "title": false}, "211": {"word": "tentative", "lemma": "tentative", "pos_tag": "NOUN", "type_entity": "", "position": 211, "title": false}, "212": {"word": "en", "lemma": "en", "pos_tag": "STOPWORD", "type_entity": "", "position": 212, "title": false}, "213": {"word": "octobre2012", "lemma": "octobre2012", "pos_tag": "NOUN", "type_entity": "", "position": 213, "title": false}, "214": {"word": ".", "lemma": ".", "pos_tag": "PUNCT", "type_entity": "", "position": 214, "title": false}, "215": {"word": "Mais", "lemma": "mais", "pos_tag": "STOPWORD", "type_entity": "", "position": 215, "title": false}, "216": {"word": "une", "lemma": "une", "pos_tag": "STOPWORD", "type_entity": "", "position": 216, "title": false}, "217": {"word": "evacuation", "lemma": "evacuation", "pos_tag": "NOUN", "type_entity": "", "position": 217, "title": false}, "218": {"word": "qui", "lemma": "qui", "pos_tag": "STOPWORD", "type_entity": "", "position": 218, "title": false}, "219": {"word": "mobiliserait", "lemma": "mobiliserait", "pos_tag": "SYM", "type_entity": "", "position": 219, "title": false}, "220": {"word": "au", "lemma": "au", "pos_tag": "STOPWORD", "type_entity": "", "position": 220, "title": false}, "221": {"word": "minimum", "lemma": "minimum", "pos_tag": "NOUN", "type_entity": "", "position": 221, "title": false}, "222": {"word": "2_000", "lemma": "2_000", "pos_tag": "NUM", "type_entity": "", "position": 222, "title": false}, "223": {"word": "gendarmes", "lemma": "gendarmes", "pos_tag": "NOUN", "type_entity": "", "position": 223, "title": true}, "224": {"word": "mobiles", "lemma": "mobiles", "pos_tag": "ADJ", "type_entity": "", "position": 224, "title": false}, "225": {"word": "s", "lemma": "s", "pos_tag": "STOPWORD", "type_entity": "", "position": 225, "title": false}, "226": {"word": "annonce", "lemma": "annonce", "pos_tag": "SYM", "type_entity": "", "position": 226, "title": false}, "227": {"word": "beaucoup", "lemma": "beaucoup", "pos_tag": "STOPWORD", "type_entity": "", "position": 227, "title": false}, "228": {"word": "plus", "lemma": "plus", "pos_tag": "STOPWORD", "type_entity": "", "position": 228, "title": true}, "229": {"word": "aisee", "lemma": "aisee", "pos_tag": "SYM", "type_entity": "", "position": 229, "title": false}, "230": {"word": "si", "lemma": "si", "pos_tag": "STOPWORD", "type_entity": "", "position": 230, "title": false}, "231": {"word": "le", "lemma": "le", "pos_tag": "STOPWORD", "type_entity": "", "position": 231, "title": false}, "232": {"word": "projet", "lemma": "projet", "pos_tag": "NOUN", "type_entity": "", "position": 232, "title": false}, "233": {"word": "d", "lemma": "d", "pos_tag": "STOPWORD", "type_entity": "", "position": 233, "title": false}, "234": {"word": "aeroport", "lemma": "aeroport", "pos_tag": "NOUN", "type_entity": "", "position": 234, "title": false}, "235": {"word": "est", "lemma": "est", "pos_tag": "STOPWORD", "type_entity": "", "position": 235, "title": false}, "236": {"word": "abandonne", "lemma": "abandonne", "pos_tag": "ADJ", "type_entity": "", "position": 236, "title": false}, "237": {"word": ".", "lemma": ".", "pos_tag": "PUNCT", "type_entity": "", "position": 237, "title": false}, "238": {"word": "Soutenues", "lemma": "soutenues", "pos_tag": "NOUN", "type_entity": "", "position": 238, "title": false}, "239": {"word": "par", "lemma": "par", "pos_tag": "STOPWORD", "type_entity": "", "position": 239, "title": false}, "240": {"word": "des", "lemma": "des", "pos_tag": "STOPWORD", "type_entity": "", "position": 240, "title": false}, "241": {"word": "ONG", "lemma": "ong", "pos_tag": "NOUN", "type_entity": "", "position": 241, "title": false}, "242": {"word": "comme", "lemma": "comme", "pos_tag": "STOPWORD", "type_entity": "", "position": 242, "title": false}, "243": {"word": "Greenpeace", "lemma": "greenpeace", "pos_tag": "PROPN", "type_entity": "", "position": 243, "title": false}, "244": {"word": "une", "lemma": "une", "pos_tag": "STOPWORD", "type_entity": "", "position": 244, "title": false}, "245": {"word": "poignee", "lemma": "poignee", "pos_tag": "NOUN", "type_entity": "", "position": 245, "title": false}, "246": {"word": "de", "lemma": "de", "pos_tag": "STOPWORD", "type_entity": "", "position": 246, "title": true}, "247": {"word": "personnes", "lemma": "personnes", "pos_tag": "NOUN", "type_entity": "", "position": 247, "title": false}, "248": {"word": "comme", "lemma": "comme", "pos_tag": "STOPWORD", "type_entity": "", "position": 248, "title": false}, "249": {"word": "l", "lemma": "l", "pos_tag": "STOPWORD", "type_entity": "", "position": 249, "title": false}, "250": {"word": "eurodepute", "lemma": "eurodepute", "pos_tag": "NOUN", "type_entity": "", "position": 250, "title": false}, "251": {"word": "Jose", "lemma": "jose", "pos_tag": "PROPN", "type_entity": "", "position": 251, "title": false}, "252": {"word": "Bove", "lemma": "bove", "pos_tag": "PROPN", "type_entity": "", "position": 252, "title": false}, "253": {"word": "ou", "lemma": "ou", "pos_tag": "STOPWORD", "type_entity": "", "position": 253, "title": false}, "254": {"word": "le", "lemma": "le", "pos_tag": "STOPWORD", "type_entity": "", "position": 254, "title": false}, "255": {"word": "depute", "lemma": "depute", "pos_tag": "NOUN", "type_entity": "", "position": 255, "title": false}, "256": {"word": "LREM", "lemma": "lrem", "pos_tag": "PROPN", "type_entity": "", "position": 256, "title": false}, "257": {"word": "Matthieu", "lemma": "matthieu", "pos_tag": "PROPN", "type_entity": "", "position": 257, "title": false}, "258": {"word": "Orphelin", "lemma": "orphelin", "pos_tag": "PROPN", "type_entity": "", "position": 258, "title": false}, "259": {"word": ",", "lemma": ",", "pos_tag": "PUNCT", "type_entity": "", "position": 259, "title": false}, "260": {"word": "plaident", "lemma": "plaident", "pos_tag": "SYM", "type_entity": "", "position": 260, "title": false}, "261": {"word": "pour", "lemma": "pour", "pos_tag": "STOPWORD", "type_entity": "", "position": 261, "title": false}, "262": {"word": "renoncer", "lemma": "renoncer", "pos_tag": "SYM", "type_entity": "", "position": 262, "title": false}, "263": {"word": "a", "lemma": "a", "pos_tag": "STOPWORD", "type_entity": "", "position": 263, "title": false}, "264": {"word": "une", "lemma": "une", "pos_tag": "STOPWORD", "type_entity": "", "position": 264, "title": false}, "265": {"word": "\"", "lemma": "\"", "pos_tag": "PUNCT", "type_entity": "", "position": 265, "title": false}, "266": {"word": "evacuation", "lemma": "evacuation", "pos_tag": "NOUN", "type_entity": "", "position": 266, "title": false}, "267": {"word": "violente", "lemma": "violente", "pos_tag": "ADJ", "type_entity": "", "position": 267, "title": false}, "268": {"word": "\"", "lemma": "\"", "pos_tag": "PUNCT", "type_entity": "", "position": 268, "title": false}, "269": {"word": "et", "lemma": "et", "pos_tag": "STOPWORD", "type_entity": "", "position": 269, "title": false}, "270": {"word": "preconisent", "lemma": "preconisent", "pos_tag": "SYM", "type_entity": "", "position": 270, "title": false}, "271": {"word": "d", "lemma": "d", "pos_tag": "STOPWORD", "type_entity": "", "position": 271, "title": false}, "272": {"word": "aller", "lemma": "aller", "pos_tag": "SYM", "type_entity": "", "position": 272, "title": false}, "273": {"word": "vers", "lemma": "vers", "pos_tag": "STOPWORD", "type_entity": "", "position": 273, "title": false}, "274": {"word": "un", "lemma": "un", "pos_tag": "STOPWORD", "type_entity": "", "position": 274, "title": false}, "275": {"word": "\"", "lemma": "\"", "pos_tag": "PUNCT", "type_entity": "", "position": 275, "title": false}, "276": {"word": "nouvel", "lemma": "nouvel", "pos_tag": "ADJ", "type_entity": "", "position": 276, "title": false}, "277": {"word": "avenir", "lemma": "avenir", "pos_tag": "NOUN", "type_entity": "", "position": 277, "title": false}, "278": {"word": "\"", "lemma": "\"", "pos_tag": "PUNCT", "type_entity": "", "position": 278, "title": false}, "279": {"word": "similaire", "lemma": "similaire", "pos_tag": "ADJ", "type_entity": "", "position": 279, "title": false}, "280": {"word": "a", "lemma": "a", "pos_tag": "STOPWORD", "type_entity": "", "position": 280, "title": false}, "281": {"word": "l", "lemma": "l", "pos_tag": "STOPWORD", "type_entity": "", "position": 281, "title": false}, "282": {"word": "experience", "lemma": "experience", "pos_tag": "NOUN", "type_entity": "", "position": 282, "title": false}, "283": {"word": "du", "lemma": "du", "pos_tag": "STOPWORD", "type_entity": "", "position": 283, "title": false}, "284": {"word": "Larzac", "lemma": "larzac", "pos_tag": "PROPN", "type_entity": "", "position": 284, "title": false}, "285": {"word": "dans", "lemma": "dans", "pos_tag": "STOPWORD", "type_entity": "", "position": 285, "title": false}, "286": {"word": "les", "lemma": "les", "pos_tag": "STOPWORD", "type_entity": "", "position": 286, "title": false}, "287": {"word": "annees", "lemma": "annees", "pos_tag": "NOUN", "type_entity": "", "position": 287, "title": false}, "288": {"word": "70", "lemma": "70", "pos_tag": "NUM", "type_entity": "", "position": 288, "title": false}, "289": {"word": ".", "lemma": ".", "pos_tag": "PUNCT", "type_entity": "", "position": 289, "title": false}, "290": {"word": "M.C.", "lemma": "m.c.", "pos_tag": "PROPN", "type_entity": "", "position": 290, "title": false}, "291": {"word": "Avec", "lemma": "avec", "pos_tag": "ADP", "type_entity": "", "position": 291, "title": false}, "292": {"word": "AFP", "lemma": "afp", "pos_tag": "PROPN", "type_entity": "", "position": 292, "title": false}, "293": {"word": "L", "lemma": "l", "pos_tag": "STOPWORD", "type_entity": "", "position": 293, "title": false}, "294": {"word": "Obs", "lemma": "obs", "pos_tag": "PROPN", "type_entity": "", "position": 294, "title": false}, "words": ["Journee", "cruciale", "a", "NotreDamedesLandes", ".", "Le", "dispositif", "policier", "se", "met", "progressivement", "en", "place", "autour", "de", "la", "ZAD", "ce", "mercredi", "mercredi17janvieralors", "que", "la", "decision", "du", "gouvernement", "pourrait", "etre", "annoncee", "en", "fin", "de", "matinee", ".", "Survolee", "par", "des", "helicopteres", "de", "la", "gendarmerie", "la", "zone", "d", "amenagement", "differe", "est", "egalement", "encerclee", "par", "sept", "escadrons", "soit", "455", "gendarmes", "mobiles", "precise", "BFMTV", ".", "Un", "deploiement", "qui", "vise", "a", "controler", "et", "securiser", "la", "zone", "de", "1_600", "hectares", "en", "prevision", "d", "une", "eventuelle", "evacuation", ".", "Selon", "l", "AFP", "plusieurs", "compagnies", "de", "CRS", "sont", "egalement", "en", "cours", "de", "positionnement", "a", "Nantes", "et", "Rennes", "au", "cas", "ou", "des", "manifestations", "seraient", "organisees", "a", "la", "suite", "de", "la", "decision", "du", "l", "executif", ".", "Car", "quelque", "soit", "la", "reponse", "du", "gouvernement", "celleci", "sera", "mauvaise", "pour", "certains", "avait", "reconnu", "des", "mardi", "le", "Premier", "ministre", "Edouard", "Philippe", "devant", "les", "deputes", "LREM", "en", "reunion", "de", "groupe", ".", "La", "ZAD", "est", "actuellement", "occupee", "par", "150", "a", "2_0", "personnes", "qui", "selon", "les", "autorites", "en", "ont", "fait", "un", "camp", "retranche", ".", "La", "zone", "sera", "evacuee", "des", "elements", "les", "plus", "radicaux", "a", "affirme", "mardi", "le", "ministre", "de", "l", "Interieur", "Gerard", "Collomb", "sur", "France", "2", ".", "Qu", "ils", "soient", "pour", "ou", "contre", "l", "aeroport", "la", "quasitotalite", "des", "elus", "locaux", "defendent", "son", "evacuation", "six", "ans", "apres", "le", "fiasco", "d", "une", "premiere", "tentative", "en", "octobre2012", ".", "Mais", "une", "evacuation", "qui", "mobiliserait", "au", "minimum", "2_000", "gendarmes", "mobiles", "s", "annonce", "beaucoup", "plus", "aisee", "si", "le", "projet", "d", "aeroport", "est", "abandonne", ".", "Soutenues", "par", "des", "ONG", "comme", "Greenpeace", "une", "poignee", "de", "personnes", "comme", "l", "eurodepute", "Jose", "Bove", "ou", "le", "depute", "LREM", "Matthieu", "Orphelin", ",", "plaident", "pour", "renoncer", "a", "une", "\"", "evacuation", "violente", "\"", "et", "preconisent", "d", "aller", "vers", "un", "\"", "nouvel", "avenir", "\"", "similaire", "a", "l", "experience", "du", "Larzac", "dans", "les", "annees", "70", ".", "M.C.", "Avec", "AFP", "L", "Obs"], "list_lemma": ["journee", "cruciale", "a", "notredamedeslandes", ".", "le", "dispositif", "policier", "se", "met", "progressivement", "en", "place", "autour", "de", "la", "zad", "ce", "mercredi", "mercredi17janvieralors", "que", "la", "decision", "du", "gouvernement", "pourrait", "etre", "annoncee", "en", "fin", "de", "matinee", ".", "survolee", "par", "des", "helicopteres", "de", "la", "gendarmerie", "la", "zone", "d", "amenagement", "differe", "est", "egalement", "encerclee", "par", "sept", "escadrons", "soit", "455", "gendarmes", "mobiles", "precise", "bfmtv", ".", "un", "deploiement", "qui", "vise", "a", "controler", "et", "securiser", "la", "zone", "de", "1_600", "hectares", "en", "prevision", "d", "une", "eventuelle", "evacuation", ".", "selon", "l", "afp", "plusieurs", "compagnies", "de", "crs", "sont", "egalement", "en", "cours", "de", "positionnement", "a", "nantes", "et", "rennes", "au", "cas", "ou", "des", "manifestations", "seraient", "organisees", "a", "la", "suite", "de", "la", "decision", "du", "l", "executif", ".", "car", "quelque", "soit", "la", "reponse", "du", "gouvernement", "celleci", "sera", "mauvaise", "pour", "certains", "avait", "reconnu", "des", "mardi", "le", "premier", "ministre", "edouard", "philippe", "devant", "les", "deputes", "lrem", "en", "reunion", "de", "groupe", ".", "la", "zad", "est", "actuellement", "occupee", "par", "150", "a", "2_0", "personnes", "qui", "selon", "les", "autorites", "en", "ont", "fait", "un", "camp", "retranche", ".", "la", "zone", "sera", "evacuee", "des", "elements", "les", "plus", "radicaux", "a", "affirme", "mardi", "le", "ministre", "de", "l", "interieur", "gerard", "collomb", "sur", "france", "2", ".", "qu", "ils", "soient", "pour", "ou", "contre", "l", "aeroport", "la", "quasitotalite", "des", "elus", "locaux", "defendent", "son", "evacuation", "six", "ans", "apres", "le", "fiasco", "d", "une", "premiere", "tentative", "en", "octobre2012", ".", "mais", "une", "evacuation", "qui", "mobiliserait", "au", "minimum", "2_000", "gendarmes", "mobiles", "s", "annonce", "beaucoup", "plus", "aisee", "si", "le", "projet", "d", "aeroport", "est", "abandonne", ".", "soutenues", "par", "des", "ong", "comme", "greenpeace", "une", "poignee", "de", "personnes", "comme", "l", "eurodepute", "jose", "bove", "ou", "le", "depute", "lrem", "matthieu", "orphelin", ",", "plaident", "pour", "renoncer", "a", "une", "\"", "evacuation", "violente", "\"", "et", "preconisent", "d", "aller", "vers", "un", "\"", "nouvel", "avenir", "\"", "similaire", "a", "l", "experience", "du", "larzac", "dans", "les", "annees", "70", ".", "m.c.", "avec", "afp", "l", "obs"]}, "theme": "Notre-Dame-des-Landes"}